LICENSE.txt
setup.py
instagramtolle/__init__.py
instagramtolle.egg-info/PKG-INFO
instagramtolle.egg-info/SOURCES.txt
instagramtolle.egg-info/dependency_links.txt
instagramtolle.egg-info/requires.txt
instagramtolle.egg-info/top_level.txt